hangarmc_hangar/__init__.py
hangarmc_hangar/exception/__init__.py
hangarmc_hangar/exception/hangar_exceptions.py
hangarmc_hangar/hangar.py
hangarmc_hangar/model/__init__.py
hangarmc_hangar/model/hangar_models.py
hangarmc_hangar/parser/__init__.py
hangarmc_hangar/parser/hangar_parsers.py
hangarmc_hangar-1.0.0.dist-info/WHEEL
hangarmc_hangar-1.0.0.dist-info/METADATA
hangarmc_hangar-1.0.0.dist-info/RECORD
