Metadata-Version: 2.1
Name: hangarmc-hangar
Version: 1.0.0
Summary: Hangar SDK for python
Home-page: https://pypi.org/project/hangarmc-hangar/
License: MIT
Author: Oskar
Author-email: 56176746+OskarZyg@users.noreply.github.com
Requires-Python: >=3.10,<4.0
Classifier: License :: OSI Approved :: MIT License
Classifier: Programming Language :: Python :: 3
Classifier: Programming Language :: Python :: 3.10
Requires-Dist: orjson (>=3.7.8,<4.0.0)
Requires-Dist: python-dateutil (>=2.8.2,<3.0.0)
Requires-Dist: urllib3 (>=1.26.11,<2.0.0)
Project-URL: Documentation, https://github.com/OskarsMC-Network/hangarmc-hangar/blob/main/README.md
Project-URL: Repository, https://github.com/OskarsMC-Network/hangarmc-hangar/
